ArgTools/__init__.py
argsls-0.0.1.dist-info/METADATA
argsls-0.0.1.dist-info/WHEEL
argsls-0.0.1.dist-info/top_level.txt
argsls-0.0.1.dist-info/RECORD
