Metadata-Version: 2.1
Name: argsls
Version: 0.0.1
Summary: Basic argument functions.
Home-page: UNKNOWN
Author: Crow Randalf
Author-email: birdpeople16@gmail.com
License: MIT
Keywords: args
Platform: UNKNOWN
Classifier: Development Status :: 5 - Production/Stable
Classifier: Intended Audience :: Education
Classifier: Operating System :: Microsoft :: Windows :: Windows 10
Classifier: License :: OSI Approved :: MIT License
Classifier: Programming Language :: Python :: 3
